openarmx_driver/__init__.py
openarmx_driver/arm.py
openarmx_driver/exceptions.py
openarmx_driver/robot.py
openarmx_driver/_lib/__init__.py
openarmx_driver/_lib/can_comm.cpython-310-x86_64-linux-gnu.so
openarmx_driver/_lib/can_utils.cpython-310-x86_64-linux-gnu.so
openarmx_driver/_lib/log_utils.cpython-310-x86_64-linux-gnu.so
openarmx_driver/_lib/motor_config_loader.cpython-310-x86_64-linux-gnu.so
openarmx_driver/_lib/motor_control.cpython-310-x86_64-linux-gnu.so
openarmx_driver/_lib/motor_manager.cpython-310-x86_64-linux-gnu.so
openarmx_driver/config/__init__.py
openarmx_driver/config/arm_direction_config.yaml
openarmx_driver/config/motor_config.yaml
openarmx_driver-1.0.1.dist-info/licenses/LICENSE
openarmx_driver-1.0.1.dist-info/METADATA
openarmx_driver-1.0.1.dist-info/WHEEL
openarmx_driver-1.0.1.dist-info/top_level.txt
openarmx_driver-1.0.1.dist-info/RECORD
