Metadata-Version: 2.4
Name: openarmx-driver
Version: 1.0.1
Summary: Python SDK for OpenArmX robotic arm control via CAN bus
Author-email: Wei Lindong <weilindong02@gmail.com>
License: OpenArmX Research and Education License
Project-URL: Homepage, https://www.openarmx.com
Project-URL: Documentation, https://docs.openarmx.com
Project-URL: Repository, https://www.openarmx.com
Project-URL: Issues, https://www.openarmx.com
Keywords: robotics,can-bus,motor-control,robstride,openarm
Classifier: Development Status :: 4 - Beta
Classifier: Intended Audience :: Developers
Classifier: Intended Audience :: Science/Research
Classifier: License :: Other/Proprietary License
Classifier: Operating System :: POSIX :: Linux
Classifier: Programming Language :: Python :: 3
Classifier: Programming Language :: Python :: 3.7
Classifier: Programming Language :: Python :: 3.8
Classifier: Programming Language :: Python :: 3.9
Classifier: Programming Language :: Python :: 3.10
Classifier: Programming Language :: Python :: 3.11
Classifier: Topic :: Scientific/Engineering
Classifier: Topic :: Software Development :: Libraries :: Python Modules
Requires-Python: >=3.7
License-File: LICENSE
Requires-Dist: python-can>=4.0.0
Requires-Dist: PyYAML>=5.4.0
Dynamic: license-file
